sphinxcontrib_runcmd-0.2.0-py3.6-nspkg.pth
sphinxcontrib/runcmd/__init__.py
sphinxcontrib/runcmd/utils.py
sphinxcontrib_runcmd-0.2.0.dist-info/LICENSE
sphinxcontrib_runcmd-0.2.0.dist-info/METADATA
sphinxcontrib_runcmd-0.2.0.dist-info/WHEEL
sphinxcontrib_runcmd-0.2.0.dist-info/namespace_packages.txt
sphinxcontrib_runcmd-0.2.0.dist-info/top_level.txt
sphinxcontrib_runcmd-0.2.0.dist-info/RECORD
