Metadata-Version: 2.1
Name: sphinxcontrib-runcmd
Version: 0.2.0
Summary: Sphinx "runcmd" extension
Home-page: https://github.com/invenia/sphinxcontrib-runcmd
Author: Fernando Chorney
Author-email: fernando.chorney@invenia.ca
License: MIT
Download-URL: https://pypi.org/project/sphinxcontrib-runcmd
Platform: any
Classifier: Development Status :: 4 - Beta
Classifier: Environment :: Console
Classifier: Environment :: Web Environment
Classifier: Intended Audience :: Developers
Classifier: License :: OSI Approved :: MIT License
Classifier: Operating System :: OS Independent
Classifier: Programming Language :: Python
Classifier: Programming Language :: Python :: 2.7
Classifier: Programming Language :: Python :: 3.6
Classifier: Topic :: Documentation
Classifier: Topic :: Utilities
Requires-Dist: sphinx
Provides-Extra: test
Requires-Dist: coverage; extra == 'test'
Requires-Dist: pytest; extra == 'test'
Requires-Dist: pytest-cov; extra == 'test'
Requires-Dist: sphinx-testing; extra == 'test'
